mwutils/__init__.py
mwutils/keras.py
mwutils/logs.py
mwutils/run.py
mwutils/sys_stat.py
mwutils/tf_utils.py
mwutils/torch_utils.py
mwutils/utils.py
modelwhaleutils-0.5.2.6.dist-info/METADATA
modelwhaleutils-0.5.2.6.dist-info/WHEEL
modelwhaleutils-0.5.2.6.dist-info/top_level.txt
modelwhaleutils-0.5.2.6.dist-info/RECORD
