Metadata-Version: 2.1
Name: modelwhaleutils
Version: 0.5.2.6
Summary: Used in modelwhale
Home-page: https://github.com/Kesci/modelwhaleutils
Author: ModelWHale Team
Project-URL: Homepage, https://github.com/Kesci/modelwhaleutils
Project-URL: Issues, https://github.com/Kesci/modelwhaleutils/issues
Classifier: Programming Language :: Python :: 3
Classifier: License :: OSI Approved :: MIT License
Classifier: Operating System :: OS Independent
Requires-Python: >=3.6
Requires-Dist: PyJWT
Requires-Dist: requests
Requires-Dist: pynvml
Requires-Dist: psutil
Requires-Dist: boto3
Requires-Dist: mlflow
